[
{
  "title": "القانون",
  "author": "القانون",
  "university": "جامعة طرابلس",
  "year": "2026",
  "status": "متوفرة"
},{
  "title": "الإنتاج الفكري الليبي في مجال القانون",
  "author": "الصديق محمود بن سليمان",
  "supervisor": "محمد الفيتوري",
  "university": "جامعة طرابلس",
  "year": "2005",
  "id": "2005",
  "status": "متوفرة"
},{
  "title": "التدريب في المكتبات",
  "author": "محمد بن موسى",
  "supervisor": "عبد الله الشريف",
  "university": "جامعة طرابلس",
  "year": "2004",
  "id": "111",
  "degree": "ماجستير",
  "status": "متوفرة"
}]
